azure/storage/fileshare/__init__.py
azure/storage/fileshare/_deserialize.py
azure/storage/fileshare/_directory_client.py
azure/storage/fileshare/_directory_client_helpers.py
azure/storage/fileshare/_download.py
azure/storage/fileshare/_file_client.py
azure/storage/fileshare/_file_client_helpers.py
azure/storage/fileshare/_lease.py
azure/storage/fileshare/_models.py
azure/storage/fileshare/_parser.py
azure/storage/fileshare/_serialize.py
azure/storage/fileshare/_share_client.py
azure/storage/fileshare/_share_client_helpers.py
azure/storage/fileshare/_share_service_client.py
azure/storage/fileshare/_share_service_client_helpers.py
azure/storage/fileshare/_shared_access_signature.py
azure/storage/fileshare/_version.py
azure/storage/fileshare/py.typed
azure/storage/fileshare/_generated/__init__.py
azure/storage/fileshare/_generated/_azure_file_storage.py
azure/storage/fileshare/_generated/_configuration.py
azure/storage/fileshare/_generated/_patch.py
azure/storage/fileshare/_generated/_serialization.py
azure/storage/fileshare/_generated/py.typed
azure/storage/fileshare/_generated/aio/__init__.py
azure/storage/fileshare/_generated/aio/_azure_file_storage.py
azure/storage/fileshare/_generated/aio/_configuration.py
azure/storage/fileshare/_generated/aio/_patch.py
azure/storage/fileshare/_generated/aio/operations/__init__.py
azure/storage/fileshare/_generated/aio/operations/_directory_operations.py
azure/storage/fileshare/_generated/aio/operations/_file_operations.py
azure/storage/fileshare/_generated/aio/operations/_patch.py
azure/storage/fileshare/_generated/aio/operations/_service_operations.py
azure/storage/fileshare/_generated/aio/operations/_share_operations.py
azure/storage/fileshare/_generated/models/__init__.py
azure/storage/fileshare/_generated/models/_azure_file_storage_enums.py
azure/storage/fileshare/_generated/models/_models_py3.py
azure/storage/fileshare/_generated/models/_patch.py
azure/storage/fileshare/_generated/operations/__init__.py
azure_storage_file_share-12.20.1.dist-info/LICENSE
azure_storage_file_share-12.20.1.dist-info/METADATA
azure_storage_file_share-12.20.1.dist-info/WHEEL
azure_storage_file_share-12.20.1.dist-info/top_level.txt
azure_storage_file_share-12.20.1.dist-info/RECORD
